MANIFEST.in
README.rst
setup.py
c2c/__init__.py
c2c.recipe.jarfile.egg-info/PKG-INFO
c2c.recipe.jarfile.egg-info/SOURCES.txt
c2c.recipe.jarfile.egg-info/dependency_links.txt
c2c.recipe.jarfile.egg-info/entry_points.txt
c2c.recipe.jarfile.egg-info/namespace_packages.txt
c2c.recipe.jarfile.egg-info/not-zip-safe
c2c.recipe.jarfile.egg-info/requires.txt
c2c.recipe.jarfile.egg-info/top_level.txt
c2c/recipe/__init__.py
c2c/recipe/jarfile/__init__.py
c2c/recipe/jarfile/buildout.py