Metadata-Version: 1.0
Name: c2c.recipe.jarfile
Version: 0.4.2
Summary: A buildout recipe to create or update jar archive file.
Home-page: http://github.com/camptocamp/c2c.recipe.jarfile
Author: Frederic Junod
Author-email: frederic.junod@camptocamp.com
License: MIT License
Platform: UNKNOWN
Classifier: Framework :: Buildout
Classifier: Intended Audience :: Developers
Classifier: Topic :: Software Development :: Build Tools
Classifier: Topic :: Software Development :: Libraries :: Python Modules
Classifier: License :: OSI Approved :: MIT License
